{
 "kind": "ComputedTableSchema",
 "id": "1217afb048502cc7d6260190b00cee92f5a7ce0b56ed04a730c037507aa61b7b",
 "isDeleted": false,
 "rev": "",
 "description": "",
 "name": "06ec8e90-d75f-1034-8fce-234ed5430b43",
 "acl": {
  "kind": "Acl",
  "owner": "",
  "aces": []
 },
 "createdDate": {
  "kind": "Date",
  "value": ""
 },
 "lastModifiedDate": {
  "kind": "Date",
  "value": ""
 },
 "urls": [],
 "tags": [],
 "meta": [
  {
   "kind": "Pair",
   "key": "SHA256",
   "value": "1217afb048502cc7d6260190b00cee92f5a7ce0b56ed04a730c037507aa61b7b"
  }
 ],
 "url": {
  "kind": "Url",
  "uri": ""
 },
 "version": "",
 "isPublic": false,
 "projectId": "",
 "folderId": "",
 "nRows": 35181,
 "columns": [
  {
   "kind": "ColumnSchema",
   "id": "97836565-a133-47a3-90b9-0fe4f611c4c2",
   "name": "umap.umap.1",
   "type": "double",
   "nRows": 0,
   "size": -1,
   "metaData": {
    "kind": "ColumnSchemaMetaData",
    "sort": [],
    "ascending": true,
    "quartiles": [],
    "properties": []
   }
  },
  {
   "kind": "ColumnSchema",
   "id": "21a5f796-7fa6-4bc4-9197-3923177ac4af",
   "name": "umap.umap.2",
   "type": "double",
   "nRows": 0,
   "size": -1,
   "metaData": {
    "kind": "ColumnSchemaMetaData",
    "sort": [],
    "ascending": true,
    "quartiles": [],
    "properties": []
   }
  },
  {
   "kind": "ColumnSchema",
   "id": "a2b8cc63-4a7a-4db7-9d49-d3c5fbd84db8",
   "name": ".ci",
   "type": "int32",
   "nRows": 0,
   "size": -1,
   "metaData": {
    "kind": "ColumnSchemaMetaData",
    "sort": [],
    "ascending": true,
    "quartiles": [],
    "properties": []
   }
  }
 ],
 "dataDirectory": "data/12/17/1217afb048502cc7d6260190b00cee92f5a7ce0b56ed04a730c037507aa61b7b",
 "relation": {
  "kind": "Relation",
  "id": "e2a31d6f-5ab5-49d2-99a5-0924d97ef280"
 },
 "query": {
  "kind": "CubeQuery",
  "relation": {
   "kind": "RenameRelation",
   "id": "b1f089be-d223-47e8-8c43-c4a67af64cc7",
   "relation": {
    "kind": "CompositeRelation",
    "id": "8d3cb26f-ac51-4627-b8aa-c96fec06e041",
    "joinOperators": [
     {
      "kind": "JoinOperator",
      "joinType": "leftOuter",
      "leftPair": {
       "kind": "ColumnPair",
       "lColumns": [
        ".ri"
       ],
       "rColumns": [
        "38d752cda8fa640c81e2784aee25127f56205f1b878e247286c9580ecf769c10._rids"
       ]
      },
      "rightRelation": {
       "kind": "SimpleRelation",
       "id": "38d752cda8fa640c81e2784aee25127f56205f1b878e247286c9580ecf769c10",
       "index": 2
      }
     }
    ],
    "mainRelation": {
     "kind": "CompositeRelation",
     "id": "10a6113d-75d4-48c7-8599-09bc2532b7bb",
     "joinOperators": [
      {
       "kind": "JoinOperator",
       "joinType": "leftOuter",
       "leftPair": {
        "kind": "ColumnPair",
        "lColumns": [
         ".ci"
        ],
        "rColumns": [
         "f9279d3367ae564d63428c47b21327ffe3c7d3491da816c854908c2e2e6b2fea._rids"
        ]
       },
       "rightRelation": {
        "kind": "SimpleRelation",
        "id": "f9279d3367ae564d63428c47b21327ffe3c7d3491da816c854908c2e2e6b2fea",
        "index": 1
       }
      }
     ],
     "mainRelation": {
      "kind": "SimpleRelation",
      "id": "0df7b354522aad83b9d1d0ff06cdef7c73a28bac59bd2c7422488ec498141490",
      "index": 0
     }
    }
   },
   "inNames": [
    "data.identity",
    ".ci",
    ".ri",
    "0df7b354522aad83b9d1d0ff06cdef7c73a28bac59bd2c7422488ec498141490._rids",
    "0df7b354522aad83b9d1d0ff06cdef7c73a28bac59bd2c7422488ec498141490.tlbId",
    "logicle..condition",
    "logicle..donor",
    "logicle..sample_id",
    "logicle..filename",
    "logicle..event_id",
    "f9279d3367ae564d63428c47b21327ffe3c7d3491da816c854908c2e2e6b2fea._rids",
    "f9279d3367ae564d63428c47b21327ffe3c7d3491da816c854908c2e2e6b2fea.tlbId",
    "marker.type",
    "logicle..marker",
    "38d752cda8fa640c81e2784aee25127f56205f1b878e247286c9580ecf769c10._rids",
    "38d752cda8fa640c81e2784aee25127f56205f1b878e247286c9580ecf769c10.tlbId",
    "logicle..condition",
    "logicle..donor",
    "logicle..sample_id",
    "logicle..filename",
    "logicle..event_id",
    "marker.type",
    "logicle..marker"
   ],
   "outNames": [
    "data.identity",
    ".ci",
    ".ri",
    "0df7b354522aad83b9d1d0ff06cdef7c73a28bac59bd2c7422488ec498141490._rids",
    "0df7b354522aad83b9d1d0ff06cdef7c73a28bac59bd2c7422488ec498141490.tlbId",
    "logicle..condition",
    "logicle..donor",
    "logicle..sample_id",
    "logicle..filename",
    "logicle..event_id",
    "f9279d3367ae564d63428c47b21327ffe3c7d3491da816c854908c2e2e6b2fea._rids",
    "f9279d3367ae564d63428c47b21327ffe3c7d3491da816c854908c2e2e6b2fea.tlbId",
    "marker.type",
    "logicle..marker",
    "38d752cda8fa640c81e2784aee25127f56205f1b878e247286c9580ecf769c10._rids",
    "38d752cda8fa640c81e2784aee25127f56205f1b878e247286c9580ecf769c10.tlbId",
    "data..condition",
    "data..donor",
    "data..sample_id",
    "data..filename",
    "data..event_id",
    "data..type",
    "data..marker"
   ]
  },
  "colColumns": [
   {
    "kind": "Factor",
    "name": "data..event_id",
    "type": "int32"
   }
  ],
  "rowColumns": [
   {
    "kind": "Factor",
    "name": "data..marker",
    "type": "string"
   }
  ],
  "axisQueries": [
   {
    "kind": "CubeAxisQuery",
    "pointSize": 4,
    "chartType": "point",
    "yAxis": {
     "kind": "Factor",
     "name": "data.identity",
     "type": "double"
    },
    "yAxisSettings": {
     "kind": "AxisSettings",
     "meta": []
    },
    "xAxis": {
     "kind": "Factor",
     "name": "",
     "type": "string"
    },
    "xAxisSettings": {
     "kind": "AxisSettings",
     "meta": []
    },
    "errors": [],
    "labels": [],
    "colors": [],
    "preprocessors": []
   }
  ],
  "filters": {
   "kind": "Filters",
   "removeNaN": true,
   "namedFilters": []
  },
  "operatorSettings": {
   "kind": "OperatorSettings",
   "namespace": "umap",
   "operatorRef": {
    "kind": "OperatorRef",
    "name": "UMAP",
    "version": "1.2.3",
    "operatorId": "5",
    "operatorKind": "ROperator",
    "propertyValues": [
     {
      "kind": "PropertyValue",
      "name": "init",
      "value": "spectral"
     },
     {
      "kind": "PropertyValue",
      "name": "scale",
      "value": "none"
     },
     {
      "kind": "PropertyValue",
      "name": "n_neighbors",
      "value": "15"
     },
     {
      "kind": "PropertyValue",
      "name": "spread",
      "value": "1"
     },
     {
      "kind": "PropertyValue",
      "name": "min_dist",
      "value": "0.5"
     },
     {
      "kind": "PropertyValue",
      "name": "pca",
      "value": "-1"
     },
     {
      "kind": "PropertyValue",
      "name": "prop.train",
      "value": "1"
     },
     {
      "kind": "PropertyValue",
      "name": "seed",
      "value": "-1"
     }
    ],
    "url": {
     "kind": "Url",
     "uri": "https://github.com/tercen/umap_operator"
    },
    "operatorSpec": {
     "kind": "OperatorSpec",
     "ontologyUri": "",
     "ontologyVersion": "",
     "inputSpecs": [],
     "outputSpecs": []
    }
   },
   "environment": [
    {
     "kind": "Pair",
     "key": "cpu",
     "value": "0"
    },
    {
     "kind": "Pair",
     "key": "ram",
     "value": "10000000000"
    },
    {
     "kind": "Pair",
     "key": "cpu-shares",
     "value": "0"
    },
    {
     "kind": "Pair",
     "key": "tercen.collect.stats",
     "value": "false"
    },
    {
     "kind": "Pair",
     "key": "debug",
     "value": "false"
    }
   ],
   "operatorModel": {
    "kind": "OperatorModel"
   }
  },
  "qtHash": "",
  "columnHash": "",
  "rowHash": ""
 }
}